pyshell/__init__.py
pyshell/pyshell.py
pyshell-0.1.1.dist-info/LICENSE
pyshell-0.1.1.dist-info/METADATA
pyshell-0.1.1.dist-info/WHEEL
pyshell-0.1.1.dist-info/top_level.txt
pyshell-0.1.1.dist-info/RECORD
