Metadata-Version: 2.1
Name: pyshell
Version: 0.1.1
Summary: A Linux subprocess module.
Home-page: https://gitlab.com/volian/pyshell
Author: volitank
Author-email: blake@volian.org
License: UNKNOWN
Project-URL: Documentation, https://volian.org/pyshell
Project-URL: Source, https://gitlab.com/volian/pyshell
Keywords: python,shell,subprocess
Platform: UNKNOWN
Classifier: Development Status :: 3 - Alpha
Classifier: Environment :: Console
Classifier: Intended Audience :: System Administrators
Classifier: Intended Audience :: Developers
Classifier: License :: OSI Approved :: GNU General Public License v3 or later (GPLv3+)
Classifier: Natural Language :: English
Classifier: Operating System :: POSIX :: Linux
Classifier: Topic :: System :: Operating System Kernels :: Linux
Classifier: Topic :: System :: Systems Administration
Classifier: Programming Language :: Python :: 3
Classifier: Programming Language :: Python :: 3.6
Classifier: Programming Language :: Python :: 3.7
Classifier: Programming Language :: Python :: 3.8
Classifier: Programming Language :: Python :: 3.9
Classifier: Programming Language :: Python :: 3 :: Only
Requires-Python: >=3.6, <4
License-File: LICENSE
Requires-Dist: pexpect
